signit/__init__.py
signit/_constants.py
signit/_helpers.py
signit/key.py
signit/signature.py
signit-0.3.0.dist-info/DESCRIPTION.rst
signit-0.3.0.dist-info/METADATA
signit-0.3.0.dist-info/RECORD
signit-0.3.0.dist-info/WHEEL
signit-0.3.0.dist-info/metadata.json
signit-0.3.0.dist-info/top_level.txt
