Metadata-Version: 2.0
Name: signit
Version: 0.3.0
Summary: HMAC signature library for http requests signing
Home-page: https://github.com/f0t0n/signit/
Author: Eugene Naydenov
Author-email: t.34.oxygen+github+signit@gmail.com
License: Apache 2
Platform: UNKNOWN
Classifier: License :: OSI Approved :: Apache Software License
Classifier: Intended Audience :: Developers
Classifier: Programming Language :: Python
Classifier: Programming Language :: Python :: 2
Classifier: Programming Language :: Python :: 2.7
Classifier: Programming Language :: Python :: 3
Classifier: Programming Language :: Python :: 3.3
Classifier: Programming Language :: Python :: 3.4
Classifier: Programming Language :: Python :: 3.5
Classifier: Programming Language :: Python :: Implementation :: CPython
Classifier: Topic :: Security
Classifier: Topic :: Security :: Cryptography
Classifier: Topic :: Software Development :: Libraries :: Python Modules
